{"name":"Walert","tagline":" JQuery plugin easy to use for display notifications.","body":"# Installation:\r\n## Dependencies:\r\n- jQuery\r\n\r\nExample:\r\n```html\r\n    <script src=\"jquery.min.js\"></script>\r\n    <script src=\"jquery.walert.js\"></script>\r\n    <script>\r\n        var notification = new Walert({\r\n            title:\"Hello World!\",//Sets the title\r\n            body:\"This is an example\"//Defines the body (supports HTML tags)\r\n        });\r\n    </script>\r\n```\r\n### Callbacks:\r\n```javascript\r\n        var notification = new Walert({\r\n            title:\"Hello World!\",\r\n            body:\"This is an example\",\r\n            onClick:function(){//Event by clicking the notification\r\n                console.log(\"Click!\");\r\n            },\r\n            onHoverIn:function(){//Event when moving the cursor in the notification\r\n                console.log(\"Hover In!\");\r\n            },\r\n            onHoverOut:function(){//Event when leaving the cursor in the notification\r\n                console.log(\"HoverOut!\");\r\n            },\r\n            onClose:function(){//Event to close the notification\r\n                console.log(\"Close!\");\r\n            },\r\n            onOpen:function(){//Event to open the notification\r\n                console.log(\"Open!\");\r\n            }\r\n        });\r\n```\r\n### Choose a icon!\r\n\r\n```javascript\r\n        var notification = new Walert({\r\n            title:\"Hello World!\",\r\n            body:\"This is an example\",\r\n            time:5000,//Time to erase(in miliseconds)\r\n            icon: \"http://hfsvt.studentrad.no/wp-content/uploads/2015/08/Earth_Globe.png\"//Sets a icon\r\n        })\r\n```\r\n\r\n### Take the property from the variable!\r\n```javascript\r\n        var notification = new Walert({\r\n            title:\"Hello World!\",\r\n            body:\"This is an example\",\r\n            time:5000,\r\n            icon: \"http://hfsvt.studentrad.no/wp-content/uploads/2015/08/Earth_Globe.png\"//Sets a icon\r\n        })\r\n        alert(\"Title:\"+notification.title);\r\n        alert(\"Body:\"+notification.body);\r\n```\r\n\r\n## You can improve this code?\r\n### Collaborate on GitHub!","google":"","note":"Don't delete this file! It's used internally to help with page regeneration."}